README.md
setup.cfg
setup.py
poda/__init__.py
poda.egg-info/PKG-INFO
poda.egg-info/SOURCES.txt
poda.egg-info/dependency_links.txt
poda.egg-info/top_level.txt
poda/application/ImageClassification.py
poda/layers/__init__.py
poda/layers/activation.py
poda/layers/convolutional.py
poda/layers/dense.py
poda/layers/lstm.py
poda/layers/merge.py
poda/layers/metrics.py
poda/layers/optimizer.py
poda/layers/regularizer.py
poda/object_detector/Yolo.py
poda/object_detector/__init__.py
poda/object_detector/utils.py
poda/preprocessing/GeneratorImage.py
poda/preprocessing/__init__.py
poda/segmentation/DeepLabV3.py
poda/segmentation/InceptionV4ResnetV2.py
poda/segmentation/Unet.py
poda/segmentation/__init__.py
poda/segmentation/train_deeplabv3.py
poda/transfer_learning/DenseNet.py
poda/transfer_learning/InceptionV3.py
poda/transfer_learning/InceptionV4.py
poda/transfer_learning/InceptionV4ResnetV2.py
poda/transfer_learning/InceptionV4_slim.py
poda/transfer_learning/NasNet.py
poda/transfer_learning/PNasNet.py
poda/transfer_learning/ResNetV1.py
poda/transfer_learning/Vgg16.py
poda/transfer_learning/Vgg16_slim.py
poda/transfer_learning/__init__.py
poda/transfer_learning/inception_utils.py
poda/transfer_learning/nasnet_utils.py
poda/transfer_learning/resnet_utils.py
poda/utils/__init__.py
poda/utils/convert_model_for_tensorflow_serving.py
poda/utils/visualize_training.py