Metadata-Version: 2.1
Name: poda
Version: 0.4.2
Summary: A package to wrap tensor operation
Home-page: UNKNOWN
Author: gideonmanurung
Author-email: gideonmanurung3@gmail.com
License: UNKNOWN
Platform: UNKNOWN
